azapy/__init__.py
azapy/Analyzers/BTADAnalyzer.py
azapy/Analyzers/BTSDAnalyzer.py
azapy/Analyzers/CVaRAnalyzer.py
azapy/Analyzers/EVaRAnalyzer.py
azapy/Analyzers/GINIAnalyzer.py
azapy/Analyzers/LSDAnalyzer.py
azapy/Analyzers/MADAnalyzer.py
azapy/Analyzers/MVAnalyzer.py
azapy/Analyzers/SDAnalyzer.py
azapy/Analyzers/SMCRAnalyzer.py
azapy/Analyzers/_RiskAnalyzer.py
azapy/Analyzers/__init__.py
azapy/Analyzers/_solvers.py
azapy/Engines/ConstWEngine.py
azapy/Engines/InvDDEngine.py
azapy/Engines/InvVarEngine.py
azapy/Engines/InvVolEngine.py
azapy/Engines/KellyEngine.py
azapy/Engines/UniversalEngine.py
azapy/Engines/_RiskEngine.py
azapy/Engines/__init__.py
azapy/Generators/ModelPipeline.py
azapy/Generators/Port_Generator.py
azapy/Generators/Port_Simple.py
azapy/Generators/__init__.py
azapy/MkT/MkTcalendar.py
azapy/MkT/MkTreader.py
azapy/MkT/__init__.py
azapy/MkT/readMkT.py
azapy/MkT/summary_MkTdata.py
azapy/MkT/update_MkTdata.py
azapy/PortOpt/Port_BTAD.py
azapy/PortOpt/Port_BTSD.py
azapy/PortOpt/Port_CVaR.py
azapy/PortOpt/Port_ConstW.py
azapy/PortOpt/Port_EVaR.py
azapy/PortOpt/Port_GINI.py
azapy/PortOpt/Port_InvDD.py
azapy/PortOpt/Port_InvVar.py
azapy/PortOpt/Port_InvVol.py
azapy/PortOpt/Port_Kelly.py
azapy/PortOpt/Port_LSD.py
azapy/PortOpt/Port_MAD.py
azapy/PortOpt/Port_MV.py
azapy/PortOpt/Port_Rebalanced.py
azapy/PortOpt/Port_SD.py
azapy/PortOpt/Port_SMCR.py
azapy/PortOpt/Port_Universal.py
azapy/PortOpt/_Port_Generator.py
azapy/PortOpt/__init__.py
azapy/Selectors/CorrClusterSelector.py
azapy/Selectors/DualMomentumSelector.py
azapy/Selectors/NullSelector.py
azapy/Selectors/__init__.py
azapy/Util/__init__.py
azapy/Util/add_cash_security.py
azapy/Util/drawdown.py
azapy/Util/gamblingKelly.py
azapy/Util/randomgen.py
azapy/Util/schedule.py
azapy-1.2.5.dist-info/LICENSE
azapy-1.2.5.dist-info/METADATA
azapy-1.2.5.dist-info/WHEEL
azapy-1.2.5.dist-info/top_level.txt
azapy-1.2.5.dist-info/RECORD
