Metadata-Version: 2.1
Name: azapy
Version: 1.2.5
Summary: Financial Portfolio Optimization Algorithms
Home-page: https://github.com/Mircea-MMXXI/azapy.git
Author: Mircea Marinescu
Author-email: mircea.marinescu@outlook.com
License: GPLv3
Project-URL: Documentation, https://azapy.readthedocs.io/en/latest
Project-URL: Source, https://github.com/Mircea-MMXXI/azapy
Project-URL: Bug Tracker, https://github.com/Mircea-MMXXI/azapy/issues
Classifier: Programming Language :: Python :: 3
Classifier: License :: OSI Approved :: GNU General Public License v3 (GPLv3)
Classifier: Operating System :: OS Independent
Requires-Python: >=3.11
License-File: LICENSE
Requires-Dist: numpy >=1.26.0
Requires-Dist: pandas >=2.2.0
Requires-Dist: scipy >=1.12.0
Requires-Dist: plotly >=5.19.0
Requires-Dist: matplotlib >=3.8.0
Requires-Dist: requests >=2.31.0
Requires-Dist: ecos >=2.0.0
Requires-Dist: pandas-market-calendars >=4.4.0
Requires-Dist: cvxopt >=1.3.2
Requires-Dist: ta >=0.11.0
Requires-Dist: yfinance >=0.2.37
Requires-Dist: statsmodels >=0.14.0
